autobench2/__init__.py
autobench2/cli.py
autobench2-0.1.3.dist-info/LICENSE
autobench2-0.1.3.dist-info/METADATA
autobench2-0.1.3.dist-info/WHEEL
autobench2-0.1.3.dist-info/entry_points.txt
autobench2-0.1.3.dist-info/top_level.txt
autobench2-0.1.3.dist-info/RECORD
