Metadata-Version: 2.1
Name: autobench2
Version: 0.1.3
Summary: HTTP benchmarking suite for wrk2
Home-page: https://github.com/cattail/autobench2
Author: Chiyu Zhong
Author-email: zhongchiyu@gmail.com
License: MIT License
Platform: UNKNOWN
Requires-Python: >=3.6.0
Requires-Dist: click (>=7.0)
